{
  "description": "Conference rankings based on CORE ranking (https://www.core.edu.au/conference-portal)",
  "last_updated": "2026-03-28",
  "rankings": {
    "A_STAR": [
      "CCS",
      "S&P",
      "USENIX Security",
      "CRYPTO",
      "EUROCRYPT",
      "NDSS",
      "PODC",
      "TCC",
      "MOBICOM",
      "CHES",
      "ASIA CCS"
    ],
    "A": [
      "ACSAC",
      "ASIACRYPT",
      "CT-RSA",
      "ESORICS",
      "PKC",
      "RAID",
      "FC",
      "CSF",
      "SOUPS",
      "PETS",
      "DIMVA",
      "ACISP",
      "ISC",
      "AsiaCCS",
      "WiSec",
      "ACNS",
      "SACMAT",
      "CNS",
      "SecureComm",
      "TrustCom",
      "ICICS",
      "ProvSec"
    ],
    "B": [
      "ACNS",
      "SCN",
      "CANS",
      "WPES",
      "DS-RT",
      "SECRYPT",
      "MILCOM"
    ]
  },
  "notes": "This file should be updated periodically from official CORE ranking or equivalent source"
}
